{"cameraMode":{"drawMode":0,"name":"Shaded","section":"Shading Mode"},"sceneLighting":true,"audioPlay":false,"sceneViewState":{"showFog":true,"showMaterialUpdate":false,"showSkybox":true,"showFlares":true,"showImageEffects":true,"showParticleSystems":true},"in2DMode":false,"pivot":{"x":-0.6604135036468506,"y":0.6737495064735413,"z":-0.5066390633583069},"rotation":{"x":-0.0706375315785408,"y":0.9213230013847351,"z":-0.19956311583518983,"w":-0.32611212134361269},"size":0.90739506483078,"orthographic":false}